[
    {
        "id": "664f14f14f26be4958ddb8dd",
        "filtered": false,
        "pending": false,
        "text": "I really like purchasing my checks from you your service is great.",
        "rating": 5,
        "labels": {
            "merged": null,
            "verification": {
                "isVerified": true,
                "createdDateTime": "2024-05-23T12:05:37.000Z",
                "reviewSourceName": "AFSv2",
                "verificationSource": "invitation",
                "verificationLevel": "verified",
                "hasDachExclusion": false
            }
        },
        "title": "You have great service ",
        "likes": 0,
        "source": "AFSv2",
        "dates": {
            "experiencedDate": "2024-04-26T00:00:00.000Z",
            "publishedDate": "2024-05-23T12:05:37.000Z",
            "updatedDate": null,
            "submittedDate": null
        },
        "report": null,
        "hasUnhandledReports": false,
        "consumer": {
            "id": "664f14ef0a274047b46f4821",
            "displayName": "JoAnn Simmons",
            "imageUrl": "",
            "numberOfReviews": 1,
            "countryCode": "US",
            "hasImage": false,
            "isVerified": false
        },
        "reply": null,
        "consumersReviewCountOnSameDomain": 1,
        "consumersReviewCountOnSameLocation": null,
        "productReviews": [],
        "language": "en",
        "location": null
    },
    {
        "id": "664ee97820caa7cd586c97c0",
        "filtered": false,
        "pending": false,
        "text": "Order delivered fast. \nNice checks",
        "rating": 5,
        "labels": {
            "merged": null,
            "verification": {
                "isVerified": true,
                "createdDateTime": "2024-05-23T09:00:08.000Z",
                "reviewSourceName": "AFSv2",
                "verificationSource": "invitation",
                "verificationLevel": "verified",
                "hasDachExclusion": false
            }
        },
        "title": "Order delivered fast",
        "likes": 0,
        "source": "AFSv2",
        "dates": {
            "experiencedDate": "2024-05-13T00:00:00.000Z",
            "publishedDate": "2024-05-23T09:00:08.000Z",
            "updatedDate": null,
            "submittedDate": null
        },
        "report": null,
        "hasUnhandledReports": false,
        "consumer": {
            "id": "5e4d822a9ecf745a033da80f",
            "displayName": "Wanda",
            "imageUrl": "",
            "numberOfReviews": 3,
            "countryCode": "US",
            "hasImage": false,
            "isVerified": false
        },
        "reply": null,
        "consumersReviewCountOnSameDomain": 1,
        "consumersReviewCountOnSameLocation": null,
        "productReviews": [],
        "language": "en",
        "location": null
    },
    {
        "id": "664ed9200ba695b58cf70d86",
        "filtered": false,
        "pending": false,
        "text": "I didn't receive any checks",
        "rating": 1,
        "labels": {
            "merged": null,
            "verification": {
                "isVerified": true,
                "createdDateTime": "2024-05-23T07:50:24.000Z",
                "reviewSourceName": "AFSv2",
                "verificationSource": "invitation",
                "verificationLevel": "verified",
                "hasDachExclusion": false
            }
        },
        "title": "I didn't receive any checks",
        "likes": 0,
        "source": "AFSv2",
        "dates": {
            "experiencedDate": "2024-03-19T00:00:00.000Z",
            "publishedDate": "2024-05-23T07:50:24.000Z",
            "updatedDate": null,
            "submittedDate": null
        },
        "report": null,
        "hasUnhandledReports": false,
        "consumer": {
            "id": "664ed91faa6fddf29e297bd6",
            "displayName": "Alma Dominguez-Rocha",
            "imageUrl": "",
            "numberOfReviews": 1,
            "countryCode": "US",
            "hasImage": false,
            "isVerified": false
        },
        "reply": {
            "message": "Hello, I am sorry to hear that your order has yet to arrive. Please email us at customer_inquiry@bgeltd.com with your order information so we can look into this for you. -Rosie",
            "publishedDate": "2024-05-24T02:08:59.000Z",
            "updatedDate": null
        },
        "consumersReviewCountOnSameDomain": 1,
        "consumersReviewCountOnSameLocation": null,
        "productReviews": [],
        "language": "en",
        "location": null
    },
    {
        "id": "664ec889bbad2b158925edda",
        "filtered": false,
        "pending": false,
        "text": "This was my first order with Bradford exchange checks. It was pretty simple to follow the instructions. I liked the selection of checks. I can’t rate the quality of the checks yet, but I’m hoping that they are as nice as they appear to be in the ad.",
        "rating": 4,
        "labels": {
            "merged": null,
            "verification": {
                "isVerified": true,
                "createdDateTime": "2024-05-23T06:39:37.000Z",
                "reviewSourceName": "AFSv2",
                "verificationSource": "invitation",
                "verificationLevel": "verified",
                "hasDachExclusion": false
            }
        },
        "title": "This was my first order with Bradford…",
        "likes": 0,
        "source": "AFSv2",
        "dates": {
            "experiencedDate": "2024-05-22T00:00:00.000Z",
            "publishedDate": "2024-05-23T06:39:37.000Z",
            "updatedDate": null,
            "submittedDate": null
        },
        "report": null,
        "hasUnhandledReports": false,
        "consumer": {
            "id": "664ec8889b26da1f2ded7a0a",
            "displayName": "Brenda Garcia",
            "imageUrl": "",
            "numberOfReviews": 1,
            "countryCode": "US",
            "hasImage": false,
            "isVerified": false
        },
        "reply": null,
        "consumersReviewCountOnSameDomain": 1,
        "consumersReviewCountOnSameLocation": null,
        "productReviews": [],
        "language": "en",
        "location": null
    },
    {
        "id": "664ec5340812c755f3cca52e",
        "filtered": false,
        "pending": false,
        "text": "Easy order. Good price. Speedy delivery",
        "rating": 5,
        "labels": {
            "merged": null,
            "verification": {
                "isVerified": true,
                "createdDateTime": "2024-05-23T06:25:24.000Z",
                "reviewSourceName": "AFSv2",
                "verificationSource": "invitation",
                "verificationLevel": "verified",
                "hasDachExclusion": false
            }
        },
        "title": "Quick checks",
        "likes": 0,
        "source": "AFSv2",
        "dates": {
            "experiencedDate": "2024-04-26T00:00:00.000Z",
            "publishedDate": "2024-05-23T06:25:24.000Z",
            "updatedDate": null,
            "submittedDate": null
        },
        "report": null,
        "hasUnhandledReports": false,
        "consumer": {
            "id": "639bc6500ae3cd00124c4c90",
            "displayName": "customer",
            "imageUrl": "",
            "numberOfReviews": 2,
            "countryCode": "US",
            "hasImage": false,
            "isVerified": false
        },
        "reply": null,
        "consumersReviewCountOnSameDomain": 1,
        "consumersReviewCountOnSameLocation": null,
        "productReviews": [],
        "language": "en",
        "location": null
    },
    {
        "id": "664ec49359d0de7c2459c884",
        "filtered": false,
        "pending": false,
        "text": "The process appeared easy. Hopefully I completed it correctly. Security and shipping were my main concern. The cost and variety of choice were important to me. ",
        "rating": 5,
        "labels": {
            "merged": null,
            "verification": {
                "isVerified": true,
                "createdDateTime": "2024-05-23T06:22:43.000Z",
                "reviewSourceName": "AFSv2",
                "verificationSource": "invitation",
                "verificationLevel": "verified",
                "hasDachExclusion": false
            }
        },
        "title": "The process appeared easy",
        "likes": 0,
        "source": "AFSv2",
        "dates": {
            "experiencedDate": "2024-05-23T00:00:00.000Z",
            "publishedDate": "2024-05-23T06:22:43.000Z",
            "updatedDate": null,
            "submittedDate": null
        },
        "report": null,
        "hasUnhandledReports": false,
        "consumer": {
            "id": "664ec492aa6fdd6d7d297386",
            "displayName": "Gladys Galka",
            "imageUrl": "",
            "numberOfReviews": 1,
            "countryCode": "US",
            "hasImage": false,
            "isVerified": false
        },
        "reply": null,
        "consumersReviewCountOnSameDomain": 1,
        "consumersReviewCountOnSameLocation": null,
        "productReviews": [],
        "language": "en",
        "location": null
    },
    {
        "id": "664ebd7308fa2fda6e93c83e",
        "filtered": false,
        "pending": false,
        "text": "We like the checks. The handling fee on top of \"free\" shipping is ridiculous.",
        "rating": 2,
        "labels": {
            "merged": null,
            "verification": {
                "isVerified": true,
                "createdDateTime": "2024-05-23T05:52:19.000Z",
                "reviewSourceName": "AFSv2",
                "verificationSource": "invitation",
                "verificationLevel": "verified",
                "hasDachExclusion": false
            }
        },
        "title": "Please get rid of the fees!",
        "likes": 0,
        "source": "AFSv2",
        "dates": {
            "experiencedDate": "2024-04-26T00:00:00.000Z",
            "publishedDate": "2024-05-23T05:52:19.000Z",
            "updatedDate": null,
            "submittedDate": null
        },
        "report": null,
        "hasUnhandledReports": false,
        "consumer": {
            "id": "664ebd729b26da5c97ed76b9",
            "displayName": "Amy",
            "imageUrl": "",
            "numberOfReviews": 1,
            "countryCode": "US",
            "hasImage": false,
            "isVerified": false
        },
        "reply": {
            "message": "Thank you for the feedback regarding your recent order. If you are in need of any assistance, please email us at customer_inquiry@bgeltd.com with your order information. -Rosie",
            "publishedDate": "2024-05-24T02:08:00.000Z",
            "updatedDate": null
        },
        "consumersReviewCountOnSameDomain": 1,
        "consumersReviewCountOnSameLocation": null,
        "productReviews": [],
        "language": "en",
        "location": null
    },
    {
        "id": "664eb5e3320266a0a5b5b677",
        "filtered": false,
        "pending": false,
        "text": "A damn scam.I clicked on the button for free shipping and then I was told I would be charged $16.95 per month.You people are despicable.I am not paying that.",
        "rating": 1,
        "labels": {
            "merged": null,
            "verification": {
                "isVerified": true,
                "createdDateTime": "2024-05-23T05:20:03.000Z",
                "reviewSourceName": "AFSv2",
                "verificationSource": "invitation",
                "verificationLevel": "verified",
                "hasDachExclusion": false
            }
        },
        "title": "A damn scam.I clicked on the button for…",
        "likes": 0,
        "source": "AFSv2",
        "dates": {
            "experiencedDate": "2024-05-22T00:00:00.000Z",
            "publishedDate": "2024-05-23T05:20:03.000Z",
            "updatedDate": null,
            "submittedDate": null
        },
        "report": null,
        "hasUnhandledReports": false,
        "consumer": {
            "id": "5bcb34394de5666d347afd63",
            "displayName": "Bob Dickerson",
            "imageUrl": "",
            "numberOfReviews": 3,
            "countryCode": "US",
            "hasImage": false,
            "isVerified": false
        },
        "reply": {
            "message": "Hello, I am sorry for any concerns regarding The Bradford Exchange Rewards Program. Please email us at customer_inquiry@bgeltd.com with your order information so we can discuss this in more detail. -",
            "publishedDate": "2024-05-24T02:07:20.000Z",
            "updatedDate": null
        },
        "consumersReviewCountOnSameDomain": 1,
        "consumersReviewCountOnSameLocation": null,
        "productReviews": [],
        "language": "en",
        "location": null
    },
    {
        "id": "664ea6ac49967fdaeee88f72",
        "filtered": false,
        "pending": false,
        "text": "Not as cumbersome as others.\n\nSelect is good, price is about reasonable.",
        "rating": 4,
        "labels": {
            "merged": null,
            "verification": {
                "isVerified": true,
                "createdDateTime": "2024-05-23T04:15:08.000Z",
                "reviewSourceName": "AFSv2",
                "verificationSource": "invitation",
                "verificationLevel": "verified",
                "hasDachExclusion": false
            }
        },
        "title": "Not as cumbersome as others.",
        "likes": 0,
        "source": "AFSv2",
        "dates": {
            "experiencedDate": "2024-05-22T00:00:00.000Z",
            "publishedDate": "2024-05-23T04:15:08.000Z",
            "updatedDate": null,
            "submittedDate": null
        },
        "report": null,
        "hasUnhandledReports": false,
        "consumer": {
            "id": "587b3a4d0000ff000a6c7c24",
            "displayName": "Israel Garza",
            "imageUrl": "",
            "numberOfReviews": 2,
            "countryCode": "US",
            "hasImage": false,
            "isVerified": false
        },
        "reply": null,
        "consumersReviewCountOnSameDomain": 1,
        "consumersReviewCountOnSameLocation": null,
        "productReviews": [],
        "language": "en",
        "location": null
    },
    {
        "id": "664ea170fd21f87d15c326dc",
        "filtered": false,
        "pending": false,
        "text": "The prices were outstanding.  There were a lot of side offers that slowed me down but ultimately I got my business checks.",
        "rating": 4,
        "labels": {
            "merged": null,
            "verification": {
                "isVerified": true,
                "createdDateTime": "2024-05-23T03:52:48.000Z",
                "reviewSourceName": "AFSv2",
                "verificationSource": "invitation",
                "verificationLevel": "verified",
                "hasDachExclusion": false
            }
        },
        "title": "The prices were outstanding",
        "likes": 0,
        "source": "AFSv2",
        "dates": {
            "experiencedDate": "2024-05-22T00:00:00.000Z",
            "publishedDate": "2024-05-23T03:52:48.000Z",
            "updatedDate": null,
            "submittedDate": null
        },
        "report": null,
        "hasUnhandledReports": false,
        "consumer": {
            "id": "548f8d1100006400019dd9bf",
            "displayName": "Chris Kelly",
            "imageUrl": "",
            "numberOfReviews": 3,
            "countryCode": "US",
            "hasImage": false,
            "isVerified": false
        },
        "reply": null,
        "consumersReviewCountOnSameDomain": 1,
        "consumersReviewCountOnSameLocation": null,
        "productReviews": [],
        "language": "en",
        "location": null
    },
    {
        "id": "664ea04bbe6709949a6322c8",
        "filtered": false,
        "pending": false,
        "text": "Too many hidden fees",
        "rating": 1,
        "labels": {
            "merged": null,
            "verification": {
                "isVerified": true,
                "createdDateTime": "2024-05-23T03:47:55.000Z",
                "reviewSourceName": "AFSv2",
                "verificationSource": "invitation",
                "verificationLevel": "verified",
                "hasDachExclusion": false
            }
        },
        "title": "Too many hidden fees",
        "likes": 0,
        "source": "AFSv2",
        "dates": {
            "experiencedDate": "2024-05-22T00:00:00.000Z",
            "publishedDate": "2024-05-23T03:47:55.000Z",
            "updatedDate": null,
            "submittedDate": null
        },
        "report": null,
        "hasUnhandledReports": false,
        "consumer": {
            "id": "664ea04aaa6fdde2be296859",
            "displayName": "Warren  Collins",
            "imageUrl": "",
            "numberOfReviews": 1,
            "countryCode": "US",
            "hasImage": false,
            "isVerified": false
        },
        "reply": {
            "message": "Thank you for the feedback regarding your recent order. If you are in need of any assistance, please email us at customer_inquiry@bgeltd.com with your order information. -Rosie",
            "publishedDate": "2024-05-24T02:06:28.000Z",
            "updatedDate": null
        },
        "consumersReviewCountOnSameDomain": 1,
        "consumersReviewCountOnSameLocation": null,
        "productReviews": [],
        "language": "en",
        "location": null
    },
    {
        "id": "664e9a992a0608029da4a540",
        "filtered": false,
        "pending": false,
        "text": "Lack of discount for returning customers, the extra fees for shipping and handling. ",
        "rating": 3,
        "labels": {
            "merged": null,
            "verification": {
                "isVerified": true,
                "createdDateTime": "2024-05-23T03:23:37.000Z",
                "reviewSourceName": "AFSv2",
                "verificationSource": "invitation",
                "verificationLevel": "verified",
                "hasDachExclusion": false
            }
        },
        "title": "Lack of discount for returning…",
        "likes": 0,
        "source": "AFSv2",
        "dates": {
            "experiencedDate": "2024-05-22T00:00:00.000Z",
            "publishedDate": "2024-05-23T03:23:37.000Z",
            "updatedDate": null,
            "submittedDate": null
        },
        "report": null,
        "hasUnhandledReports": false,
        "consumer": {
            "id": "664e9a983062a000ebfb3e51",
            "displayName": "Kelly",
            "imageUrl": "",
            "numberOfReviews": 1,
            "countryCode": "US",
            "hasImage": false,
            "isVerified": false
        },
        "reply": {
            "message": "Thank you for the feedback regarding your recent order. If you are in need of any assistance, please email us at customer_inquiry@bgeltd.com with your order information. -Rosie",
            "publishedDate": "2024-05-24T02:06:24.000Z",
            "updatedDate": null
        },
        "consumersReviewCountOnSameDomain": 1,
        "consumersReviewCountOnSameLocation": null,
        "productReviews": [],
        "language": "en",
        "location": null
    },
    {
        "id": "664e8a855489df5cde9413e9",
        "filtered": false,
        "pending": false,
        "text": "I paid for rush order and it been a week and a half and I still haven't received my order ",
        "rating": 1,
        "labels": {
            "merged": null,
            "verification": {
                "isVerified": true,
                "createdDateTime": "2024-05-23T02:15:02.000Z",
                "reviewSourceName": "AFSv2",
                "verificationSource": "invitation",
                "verificationLevel": "verified",
                "hasDachExclusion": false
            }
        },
        "title": "I paid for rush order and it been a…",
        "likes": 0,
        "source": "AFSv2",
        "dates": {
            "experiencedDate": "2024-05-11T00:00:00.000Z",
            "publishedDate": "2024-05-23T02:15:02.000Z",
            "updatedDate": null,
            "submittedDate": null
        },
        "report": null,
        "hasUnhandledReports": false,
        "consumer": {
            "id": "664e8a84aa6fdd4cce295fc6",
            "displayName": "Brent Turnquist",
            "imageUrl": "",
            "numberOfReviews": 1,
            "countryCode": "US",
            "hasImage": false,
            "isVerified": false
        },
        "reply": {
            "message": "Hello, I am sorry to hear that your order has yet to arrive. Please email us at customer_inquiry@bgeltd.com with your order information so we can look into this for you. -Rosie",
            "publishedDate": "2024-05-24T02:05:49.000Z",
            "updatedDate": null
        },
        "consumersReviewCountOnSameDomain": 1,
        "consumersReviewCountOnSameLocation": null,
        "productReviews": [],
        "language": "en",
        "location": null
    },
    {
        "id": "664e8a5f29ebbf4221cb31c2",
        "filtered": false,
        "pending": false,
        "text": "everything was perfect",
        "rating": 5,
        "labels": {
            "merged": null,
            "verification": {
                "isVerified": true,
                "createdDateTime": "2024-05-23T02:14:23.000Z",
                "reviewSourceName": "AFSv2",
                "verificationSource": "invitation",
                "verificationLevel": "verified",
                "hasDachExclusion": false
            }
        },
        "title": "everything was perfect",
        "likes": 0,
        "source": "AFSv2",
        "dates": {
            "experiencedDate": "2024-05-08T00:00:00.000Z",
            "publishedDate": "2024-05-23T02:14:23.000Z",
            "updatedDate": null,
            "submittedDate": null
        },
        "report": null,
        "hasUnhandledReports": false,
        "consumer": {
            "id": "664e8a5ef6be8965e19a39e8",
            "displayName": "Susan Block",
            "imageUrl": "",
            "numberOfReviews": 1,
            "countryCode": "US",
            "hasImage": false,
            "isVerified": false
        },
        "reply": null,
        "consumersReviewCountOnSameDomain": 1,
        "consumersReviewCountOnSameLocation": null,
        "productReviews": [],
        "language": "en",
        "location": null
    },
    {
        "id": "664e80098b51e0e44280a6ea",
        "filtered": false,
        "pending": false,
        "text": "This company embeded membership in the check order and subsequently charge monthly fee.  BE AWARE! ",
        "rating": 1,
        "labels": {
            "merged": null,
            "verification": {
                "isVerified": true,
                "createdDateTime": "2024-05-23T01:30:17.000Z",
                "reviewSourceName": "AFSv2",
                "verificationSource": "invitation",
                "verificationLevel": "verified",
                "hasDachExclusion": false
            }
        },
        "title": "Hidden MONTHLY charge",
        "likes": 0,
        "source": "AFSv2",
        "dates": {
            "experiencedDate": "2024-03-18T00:00:00.000Z",
            "publishedDate": "2024-05-23T01:30:17.000Z",
            "updatedDate": null,
            "submittedDate": null
        },
        "report": null,
        "hasUnhandledReports": false,
        "consumer": {
            "id": "664e8008f6be89176e9a34d2",
            "displayName": "LieLing Wu",
            "imageUrl": "",
            "numberOfReviews": 1,
            "countryCode": "US",
            "hasImage": false,
            "isVerified": false
        },
        "reply": {
            "message": "Hello, I am sorry for any concerns regarding The Bradford Exchange Rewards Program. Please email us at customer_inquiry@bgeltd.com with your order information so we can discuss this in more detail. -Rosie",
            "publishedDate": "2024-05-24T02:04:56.000Z",
            "updatedDate": null
        },
        "consumersReviewCountOnSameDomain": 1,
        "consumersReviewCountOnSameLocation": null,
        "productReviews": [],
        "language": "en",
        "location": null
    },
    {
        "id": "664e760b5073e7d468054758",
        "filtered": false,
        "pending": false,
        "text": "Firstly the price was increased from my order amount. Then when I asked order be cancelled (too expensive) I got a response that it was too late. When order came my name was incorrectly spelled even though it was correct on the label. I was told that having ordered online there is nothing they will do. When you pay more to order by phone they will make corrections.",
        "rating": 1,
        "labels": {
            "merged": null,
            "verification": {
                "isVerified": true,
                "createdDateTime": "2024-05-23T00:47:39.000Z",
                "reviewSourceName": "AFSv2",
                "verificationSource": "invitation",
                "verificationLevel": "verified",
                "hasDachExclusion": false
            }
        },
        "title": "Firstly the price was increased from my…",
        "likes": 0,
        "source": "AFSv2",
        "dates": {
            "experiencedDate": "2024-05-09T00:00:00.000Z",
            "publishedDate": "2024-05-23T00:47:39.000Z",
            "updatedDate": null,
            "submittedDate": null
        },
        "report": null,
        "hasUnhandledReports": false,
        "consumer": {
            "id": "664e7609aa6fddfa5c2954a5",
            "displayName": "Dianna  McIntosh",
            "imageUrl": "",
            "numberOfReviews": 1,
            "countryCode": "US",
            "hasImage": false,
            "isVerified": false
        },
        "reply": {
            "message": "Hello, I am sorry to hear that you are less than happy with your order. If you are in need of any assistance, please email us at customer_inquiry@bgeltd.com with your order information. -Rosie",
            "publishedDate": "2024-05-24T02:04:32.000Z",
            "updatedDate": null
        },
        "consumersReviewCountOnSameDomain": 1,
        "consumersReviewCountOnSameLocation": null,
        "productReviews": [],
        "language": "en",
        "location": null
    },
    {
        "id": "664e754d881d8154c920bcae",
        "filtered": false,
        "pending": false,
        "text": "Great checks with cute designs! Easy to reorder!",
        "rating": 5,
        "labels": {
            "merged": null,
            "verification": {
                "isVerified": true,
                "createdDateTime": "2024-05-23T00:44:29.000Z",
                "reviewSourceName": "AFSv2",
                "verificationSource": "invitation",
                "verificationLevel": "verified",
                "hasDachExclusion": false
            }
        },
        "title": "Great checks with cute designs",
        "likes": 0,
        "source": "AFSv2",
        "dates": {
            "experiencedDate": "2024-05-22T00:00:00.000Z",
            "publishedDate": "2024-05-23T00:44:29.000Z",
            "updatedDate": null,
            "submittedDate": null
        },
        "report": null,
        "hasUnhandledReports": false,
        "consumer": {
            "id": "664e754cf6be899bd99a2df2",
            "displayName": "Denise Vitale",
            "imageUrl": "",
            "numberOfReviews": 1,
            "countryCode": "US",
            "hasImage": false,
            "isVerified": false
        },
        "reply": null,
        "consumersReviewCountOnSameDomain": 1,
        "consumersReviewCountOnSameLocation": null,
        "productReviews": [],
        "language": "en",
        "location": null
    },
    {
        "id": "664e74d993c963bd8ea387f6",
        "filtered": false,
        "pending": false,
        "text": "I was not aware of a 11.98 handling fee. Very misleading.  It was 4 boxes for 11.98, but after the fees it was 31.98. I will never recommend this company.  They are a joke.",
        "rating": 1,
        "labels": {
            "merged": null,
            "verification": {
                "isVerified": true,
                "createdDateTime": "2024-05-23T00:42:33.000Z",
                "reviewSourceName": "AFSv2",
                "verificationSource": "invitation",
                "verificationLevel": "verified",
                "hasDachExclusion": false
            }
        },
        "title": "I was not aware of a 11.98 handling…",
        "likes": 0,
        "source": "AFSv2",
        "dates": {
            "experiencedDate": "2024-05-22T00:00:00.000Z",
            "publishedDate": "2024-05-23T00:42:33.000Z",
            "updatedDate": null,
            "submittedDate": null
        },
        "report": null,
        "hasUnhandledReports": false,
        "consumer": {
            "id": "664e74d72c441ac4bc6f6ded",
            "displayName": "Barbara Loftus",
            "imageUrl": "",
            "numberOfReviews": 1,
            "countryCode": "US",
            "hasImage": false,
            "isVerified": false
        },
        "reply": {
            "message": "Hello, I am sorry for any concerns you have with the billing of your order. Please email us at customer_inquiry@bgeltd.com with your order information if you are in need of any assistance. -Rosie",
            "publishedDate": "2024-05-24T02:03:05.000Z",
            "updatedDate": null
        },
        "consumersReviewCountOnSameDomain": 1,
        "consumersReviewCountOnSameLocation": null,
        "productReviews": [],
        "language": "en",
        "location": null
    },
    {
        "id": "664e7188fbf141c43842b038",
        "filtered": false,
        "pending": false,
        "text": ":o) :O) ;0) ! ",
        "rating": 4,
        "labels": {
            "merged": null,
            "verification": {
                "isVerified": true,
                "createdDateTime": "2024-05-23T00:28:24.000Z",
                "reviewSourceName": "AFSv2",
                "verificationSource": "invitation",
                "verificationLevel": "verified",
                "hasDachExclusion": false
            }
        },
        "title": ":o) !",
        "likes": 0,
        "source": "AFSv2",
        "dates": {
            "experiencedDate": "2024-05-22T00:00:00.000Z",
            "publishedDate": "2024-05-23T00:28:24.000Z",
            "updatedDate": null,
            "submittedDate": null
        },
        "report": null,
        "hasUnhandledReports": false,
        "consumer": {
            "id": "5dd438400410535fe643ba36",
            "displayName": "Heather",
            "imageUrl": "https://user-images.trustpilot.com/5dd438400410535fe643ba36/73x73.png",
            "numberOfReviews": 3,
            "countryCode": "US",
            "hasImage": true,
            "isVerified": false
        },
        "reply": null,
        "consumersReviewCountOnSameDomain": 1,
        "consumersReviewCountOnSameLocation": null,
        "productReviews": [],
        "language": "en",
        "location": null
    },
    {
        "id": "664e6c6a9fbf5862c4b64d33",
        "filtered": false,
        "pending": false,
        "text": "The price was very fair and I got an extra box for free. The delivery time was average and the checks arrived correctly. I will be using this company for all of my checking needs.",
        "rating": 5,
        "labels": {
            "merged": null,
            "verification": {
                "isVerified": true,
                "createdDateTime": "2024-05-23T00:06:34.000Z",
                "reviewSourceName": "AFSv2",
                "verificationSource": "invitation",
                "verificationLevel": "verified",
                "hasDachExclusion": false
            }
        },
        "title": "The price was very fair and I got an…",
        "likes": 0,
        "source": "AFSv2",
        "dates": {
            "experiencedDate": "2024-05-08T00:00:00.000Z",
            "publishedDate": "2024-05-23T00:06:34.000Z",
            "updatedDate": null,
            "submittedDate": null
        },
        "report": null,
        "hasUnhandledReports": false,
        "consumer": {
            "id": "664e6c6a2c441a36486f6957",
            "displayName": "Denise Baker",
            "imageUrl": "",
            "numberOfReviews": 1,
            "countryCode": "US",
            "hasImage": false,
            "isVerified": false
        },
        "reply": null,
        "consumersReviewCountOnSameDomain": 1,
        "consumersReviewCountOnSameLocation": null,
        "productReviews": [],
        "language": "en",
        "location": null
    }
]