[
    {
        "id": "557ed0fc0000ff0002ee3636",
        "filtered": false,
        "pending": false,
        "text": "The ordering process is very easy and doesn't take a lot of time to accomplish.  I did however expect the checks to look different than when it arrived.  I had put a picture to go on the checks but it did not appear on any of them but as I said for the most part everything was easy.\r\n\r\nThank You",
        "rating": 3,
        "labels": {
            "merged": null,
            "verification": {
                "isVerified": true,
                "createdDateTime": "2015-06-15T13:19:56.000Z",
                "reviewSourceName": "AFS",
                "verificationSource": "invitation",
                "verificationLevel": null,
                "hasDachExclusion": false
            }
        },
        "title": "Easy order form",
        "likes": 0,
        "source": "AFS",
        "dates": {
            "experiencedDate": null,
            "publishedDate": "2015-06-15T13:19:56.000Z",
            "updatedDate": null,
            "submittedDate": null
        },
        "report": null,
        "hasUnhandledReports": false,
        "consumer": {
            "id": "557ed0fc0000ff0001c6151d",
            "displayName": "Buddy Raines",
            "imageUrl": "",
            "numberOfReviews": 1,
            "countryCode": "US",
            "hasImage": false,
            "isVerified": false
        },
        "reply": {
            "message": "Hello Valued Customer \n\nThank you for your order \n\nWe are sorry to hear that you are unsatisfied with the missing picture from your order.\n\nPlease feel free to contact us at 1-708-613-2452 or info@carouselchecks.com, we are available Monday - Friday 8am to 7pm CST.",
            "publishedDate": "2015-06-15T15:32:51.267Z",
            "updatedDate": null
        },
        "consumersReviewCountOnSameDomain": 1,
        "consumersReviewCountOnSameLocation": null,
        "productReviews": [],
        "language": "en",
        "location": null
    },
    {
        "id": "557ecd650000ff0002ee3523",
        "filtered": false,
        "pending": false,
        "text": "I was concerned about ordering checks online, but ordering from Carousel was so easy from the beginning to the check out process.  Checks arrived quickly and are high quality...but the price is so affordable...so glad my daughter found this for me..now she wants to order.",
        "rating": 5,
        "labels": {
            "merged": null,
            "verification": {
                "isVerified": true,
                "createdDateTime": "2015-06-15T13:04:37.343Z",
                "reviewSourceName": "AFS",
                "verificationSource": "invitation",
                "verificationLevel": null,
                "hasDachExclusion": false
            }
        },
        "title": "Great Experience!!!",
        "likes": 0,
        "source": "AFS",
        "dates": {
            "experiencedDate": null,
            "publishedDate": "2015-06-15T13:04:37.343Z",
            "updatedDate": null,
            "submittedDate": null
        },
        "report": null,
        "hasUnhandledReports": false,
        "consumer": {
            "id": "557ecd650000ff0001c6144b",
            "displayName": "Florence Price",
            "imageUrl": "",
            "numberOfReviews": 1,
            "countryCode": "US",
            "hasImage": false,
            "isVerified": false
        },
        "reply": null,
        "consumersReviewCountOnSameDomain": 1,
        "consumersReviewCountOnSameLocation": null,
        "productReviews": [],
        "language": "en",
        "location": null
    },
    {
        "id": "557ebea20000ff0002ee303f",
        "filtered": false,
        "pending": false,
        "text": "Checks were fine. Be careful of the nickel and diming. Shipping was WAY too slow. First class mail would have been cheaper and much faster !!",
        "rating": 4,
        "labels": {
            "merged": null,
            "verification": {
                "isVerified": true,
                "createdDateTime": "2015-06-15T12:01:38.584Z",
                "reviewSourceName": "AFS",
                "verificationSource": "invitation",
                "verificationLevel": null,
                "hasDachExclusion": false
            }
        },
        "title": "So so",
        "likes": 0,
        "source": "AFS",
        "dates": {
            "experiencedDate": null,
            "publishedDate": "2015-06-15T12:01:38.584Z",
            "updatedDate": null,
            "submittedDate": null
        },
        "report": null,
        "hasUnhandledReports": false,
        "consumer": {
            "id": "557ebea20000ff0001c61077",
            "displayName": "MLB",
            "imageUrl": "",
            "numberOfReviews": 2,
            "countryCode": "US",
            "hasImage": false,
            "isVerified": false
        },
        "reply": null,
        "consumersReviewCountOnSameDomain": 1,
        "consumersReviewCountOnSameLocation": null,
        "productReviews": [],
        "language": "en",
        "location": null
    },
    {
        "id": "557ebace0000ff0002ee2f17",
        "filtered": false,
        "pending": false,
        "text": "We have ordered multiple times from them now because the products are great, ships quickly and they are economical.",
        "rating": 5,
        "labels": {
            "merged": null,
            "verification": {
                "isVerified": true,
                "createdDateTime": "2015-06-15T11:45:18.327Z",
                "reviewSourceName": "AFS",
                "verificationSource": "invitation",
                "verificationLevel": null,
                "hasDachExclusion": false
            }
        },
        "title": "Great looking, Timely and Economical",
        "likes": 0,
        "source": "AFS",
        "dates": {
            "experiencedDate": null,
            "publishedDate": "2015-06-15T11:45:18.327Z",
            "updatedDate": null,
            "submittedDate": null
        },
        "report": null,
        "hasUnhandledReports": false,
        "consumer": {
            "id": "557ebace0000ff0001c60f9d",
            "displayName": "Tabitha Magness",
            "imageUrl": "",
            "numberOfReviews": 1,
            "countryCode": "US",
            "hasImage": false,
            "isVerified": false
        },
        "reply": null,
        "consumersReviewCountOnSameDomain": 1,
        "consumersReviewCountOnSameLocation": null,
        "productReviews": [],
        "language": "en",
        "location": null
    },
    {
        "id": "557eace70000ff0002ee2ab8",
        "filtered": false,
        "pending": false,
        "text": "My order came in a timely way and was exactly what I wanted. \r\nThe price was very reasonable. TYhanks!",
        "rating": 4,
        "labels": {
            "merged": null,
            "verification": {
                "isVerified": true,
                "createdDateTime": "2015-06-15T10:45:59.366Z",
                "reviewSourceName": "AFS",
                "verificationSource": "invitation",
                "verificationLevel": null,
                "hasDachExclusion": false
            }
        },
        "title": "Satisfied",
        "likes": 0,
        "source": "AFS",
        "dates": {
            "experiencedDate": null,
            "publishedDate": "2015-06-15T10:45:59.366Z",
            "updatedDate": null,
            "submittedDate": null
        },
        "report": null,
        "hasUnhandledReports": false,
        "consumer": {
            "id": "557eace70000ff0001c60c20",
            "displayName": "Paula McCarty",
            "imageUrl": "",
            "numberOfReviews": 1,
            "countryCode": "US",
            "hasImage": false,
            "isVerified": false
        },
        "reply": null,
        "consumersReviewCountOnSameDomain": 1,
        "consumersReviewCountOnSameLocation": null,
        "productReviews": [],
        "language": "en",
        "location": null
    },
    {
        "id": "557eacb30000ff0002ee2aa5",
        "filtered": false,
        "pending": false,
        "text": "Low Cost, Fast Service",
        "rating": 5,
        "labels": {
            "merged": null,
            "verification": {
                "isVerified": true,
                "createdDateTime": "2015-06-15T10:45:07.554Z",
                "reviewSourceName": "AFS",
                "verificationSource": "invitation",
                "verificationLevel": null,
                "hasDachExclusion": false
            }
        },
        "title": "Excellent and Fast",
        "likes": 0,
        "source": "AFS",
        "dates": {
            "experiencedDate": null,
            "publishedDate": "2015-06-15T10:45:07.554Z",
            "updatedDate": null,
            "submittedDate": null
        },
        "report": null,
        "hasUnhandledReports": false,
        "consumer": {
            "id": "557eacb30000ff0001c60c12",
            "displayName": "Spring Mountain Holdings LLC",
            "imageUrl": "",
            "numberOfReviews": 1,
            "countryCode": "US",
            "hasImage": false,
            "isVerified": false
        },
        "reply": null,
        "consumersReviewCountOnSameDomain": 1,
        "consumersReviewCountOnSameLocation": null,
        "productReviews": [],
        "language": "en",
        "location": null
    },
    {
        "id": "557e30440000ff0002ee12ad",
        "filtered": false,
        "pending": false,
        "text": "I paid for the in plant rush and the faster shipping....I think they are walking them to me!! Don't bother! If you call...they will just tell you what you know, they shipped 2 weeks ago! Who orders checks, pays extra IF YOU DONT need the right away!",
        "rating": 1,
        "labels": {
            "merged": null,
            "verification": {
                "isVerified": true,
                "createdDateTime": "2015-06-15T01:54:12.000Z",
                "reviewSourceName": "AFS",
                "verificationSource": "invitation",
                "verificationLevel": null,
                "hasDachExclusion": false
            }
        },
        "title": "terrible!",
        "likes": 0,
        "source": "AFS",
        "dates": {
            "experiencedDate": null,
            "publishedDate": "2015-06-15T01:54:12.000Z",
            "updatedDate": null,
            "submittedDate": null
        },
        "report": null,
        "hasUnhandledReports": false,
        "consumer": {
            "id": "557e30440000ff0001c5f91f",
            "displayName": "Janann Gertsch",
            "imageUrl": "https://user-images.trustpilot.com/557e30440000ff0001c5f91f/73x73.png",
            "numberOfReviews": 1,
            "countryCode": "US",
            "hasImage": true,
            "isVerified": false
        },
        "reply": {
            "message": "Hello Janann \n\nThank you for your order!\n\nWe are sorry to hear that you are unsatisfied with the shipping time frame of your order.\n\nPlease feel free to contact us at 1-708-613-2452 or info@carouselchecks.com, we are available Monday - Friday 8am to 7pm CST.",
            "publishedDate": "2015-06-15T16:00:23.923Z",
            "updatedDate": null
        },
        "consumersReviewCountOnSameDomain": 1,
        "consumersReviewCountOnSameLocation": null,
        "productReviews": [],
        "language": "en",
        "location": null
    },
    {
        "id": "557e24870000ff0002ee11fa",
        "filtered": false,
        "pending": false,
        "text": "Ordering was easy, directions are clear, and checks were received in the time promised.",
        "rating": 5,
        "labels": {
            "merged": null,
            "verification": {
                "isVerified": true,
                "createdDateTime": "2015-06-15T01:04:07.662Z",
                "reviewSourceName": "AFS",
                "verificationSource": "invitation",
                "verificationLevel": null,
                "hasDachExclusion": false
            }
        },
        "title": "Carousel Check review",
        "likes": 0,
        "source": "AFS",
        "dates": {
            "experiencedDate": null,
            "publishedDate": "2015-06-15T01:04:07.662Z",
            "updatedDate": null,
            "submittedDate": null
        },
        "report": null,
        "hasUnhandledReports": false,
        "consumer": {
            "id": "557e24870000ff0001c5f86a",
            "displayName": "Cynthia Hall",
            "imageUrl": "",
            "numberOfReviews": 1,
            "countryCode": "US",
            "hasImage": false,
            "isVerified": false
        },
        "reply": null,
        "consumersReviewCountOnSameDomain": 1,
        "consumersReviewCountOnSameLocation": null,
        "productReviews": [],
        "language": "en",
        "location": null
    },
    {
        "id": "557ddeef0000ff0002ee0905",
        "filtered": false,
        "pending": false,
        "text": "First time customer. Will re-order my business checks from here next time.",
        "rating": 5,
        "labels": {
            "merged": null,
            "verification": {
                "isVerified": true,
                "createdDateTime": "2015-06-14T20:07:11.681Z",
                "reviewSourceName": "AFS",
                "verificationSource": "invitation",
                "verificationLevel": null,
                "hasDachExclusion": false
            }
        },
        "title": "Fast Easy Economical",
        "likes": 0,
        "source": "AFS",
        "dates": {
            "experiencedDate": null,
            "publishedDate": "2015-06-14T20:07:11.681Z",
            "updatedDate": null,
            "submittedDate": null
        },
        "report": null,
        "hasUnhandledReports": false,
        "consumer": {
            "id": "557ddeef0000ff0001c5f0bf",
            "displayName": "Murray Stewart Pearlman",
            "imageUrl": "",
            "numberOfReviews": 1,
            "countryCode": "US",
            "hasImage": false,
            "isVerified": false
        },
        "reply": null,
        "consumersReviewCountOnSameDomain": 1,
        "consumersReviewCountOnSameLocation": null,
        "productReviews": [],
        "language": "en",
        "location": null
    },
    {
        "id": "557dcf660000ff0002ee0531",
        "filtered": false,
        "pending": false,
        "text": "this is simple nice.",
        "rating": 5,
        "labels": {
            "merged": null,
            "verification": {
                "isVerified": false,
                "createdDateTime": "2015-06-14T19:00:54.037Z",
                "reviewSourceName": "Trustpilot",
                "verificationSource": "invitation",
                "verificationLevel": null,
                "hasDachExclusion": false
            }
        },
        "title": "title review",
        "likes": 0,
        "source": "Trustpilot",
        "dates": {
            "experiencedDate": null,
            "publishedDate": "2015-06-14T19:00:54.037Z",
            "updatedDate": null,
            "submittedDate": null
        },
        "report": null,
        "hasUnhandledReports": false,
        "consumer": {
            "id": "556ffab90000ff0001c39972",
            "displayName": "Azimuswan 'sHipar",
            "imageUrl": "https://user-images.trustpilot.com/556ffab90000ff0001c39972/73x73.png",
            "numberOfReviews": 1,
            "countryCode": "BD",
            "hasImage": true,
            "isVerified": false
        },
        "reply": null,
        "consumersReviewCountOnSameDomain": 1,
        "consumersReviewCountOnSameLocation": null,
        "productReviews": [],
        "language": "en",
        "location": null
    },
    {
        "id": "557dc5550000ff0002ee0291",
        "filtered": false,
        "pending": false,
        "text": "On my checks I made them safe,  By putting on them ask for ID ,and a large F for my last name in the corner,  Very clean and neat looking,  A person checks says a lot about the person who is writing them,  I made a mistake on them,  after they arrived I saw what I did, the company redid them at a lower cost,   Though it was my fault, that is what you call great customer service above and beyond",
        "rating": 5,
        "labels": {
            "merged": null,
            "verification": {
                "isVerified": true,
                "createdDateTime": "2015-06-14T18:17:57.803Z",
                "reviewSourceName": "AFS",
                "verificationSource": "invitation",
                "verificationLevel": null,
                "hasDachExclusion": false
            }
        },
        "title": "great looking check",
        "likes": 0,
        "source": "AFS",
        "dates": {
            "experiencedDate": null,
            "publishedDate": "2015-06-14T18:17:57.803Z",
            "updatedDate": null,
            "submittedDate": null
        },
        "report": null,
        "hasUnhandledReports": false,
        "consumer": {
            "id": "55536db90000ff0001bec399",
            "displayName": "Anthony Fabiano",
            "imageUrl": "https://user-images.trustpilot.com/55536db90000ff0001bec399/73x73.png",
            "numberOfReviews": 3,
            "countryCode": "US",
            "hasImage": true,
            "isVerified": false
        },
        "reply": null,
        "consumersReviewCountOnSameDomain": 1,
        "consumersReviewCountOnSameLocation": null,
        "productReviews": [],
        "language": "en",
        "location": null
    },
    {
        "id": "557db42c0000ff0002edfe25",
        "filtered": false,
        "pending": false,
        "text": "Your e mail said the checks shipped on 6-5-15. As of 6-13-15 no checks and I payed for two day shipping. Will not use your service Again!!!!",
        "rating": 1,
        "labels": {
            "merged": null,
            "verification": {
                "isVerified": true,
                "createdDateTime": "2015-06-14T17:04:44.000Z",
                "reviewSourceName": "AFS",
                "verificationSource": "invitation",
                "verificationLevel": null,
                "hasDachExclusion": false
            }
        },
        "title": "No checks",
        "likes": 0,
        "source": "AFS",
        "dates": {
            "experiencedDate": null,
            "publishedDate": "2015-06-14T17:04:44.000Z",
            "updatedDate": null,
            "submittedDate": null
        },
        "report": null,
        "hasUnhandledReports": false,
        "consumer": {
            "id": "557db42c0000ff0001c5e854",
            "displayName": "steve yuhasz",
            "imageUrl": "",
            "numberOfReviews": 1,
            "countryCode": "US",
            "hasImage": false,
            "isVerified": false
        },
        "reply": {
            "message": "Hello Steve\n\nThank you for your order!\n\nWe are sorry to hear that you are unsatisfied with the shipping time frame of your order.\n\nPlease feel free to contact us at 1-708-613-2452 or info@carouselchecks.com, we are available Monday - Friday 8am to 7pm CST.",
            "publishedDate": "2015-06-15T16:24:01.864Z",
            "updatedDate": null
        },
        "consumersReviewCountOnSameDomain": 1,
        "consumersReviewCountOnSameLocation": null,
        "productReviews": [],
        "language": "en",
        "location": null
    },
    {
        "id": "557db0b70000ff0002edfd61",
        "filtered": false,
        "pending": false,
        "text": "I'm very pleased with the timely manner I received my checks. The prices are excellent and so are the choices.",
        "rating": 5,
        "labels": {
            "merged": null,
            "verification": {
                "isVerified": true,
                "createdDateTime": "2015-06-14T16:49:59.128Z",
                "reviewSourceName": "AFS",
                "verificationSource": "invitation",
                "verificationLevel": null,
                "hasDachExclusion": false
            }
        },
        "title": "Very pleased",
        "likes": 0,
        "source": "AFS",
        "dates": {
            "experiencedDate": null,
            "publishedDate": "2015-06-14T16:49:59.128Z",
            "updatedDate": null,
            "submittedDate": null
        },
        "report": null,
        "hasUnhandledReports": false,
        "consumer": {
            "id": "557db0b70000ff0001c5e7b7",
            "displayName": "Dawn Thomas",
            "imageUrl": "",
            "numberOfReviews": 1,
            "countryCode": "US",
            "hasImage": false,
            "isVerified": false
        },
        "reply": null,
        "consumersReviewCountOnSameDomain": 1,
        "consumersReviewCountOnSameLocation": null,
        "productReviews": [],
        "language": "en",
        "location": null
    },
    {
        "id": "557d9f4d0000ff0002edf95e",
        "filtered": false,
        "pending": false,
        "text": "The checks were delivered in a high quality/timely manner!!",
        "rating": 5,
        "labels": {
            "merged": null,
            "verification": {
                "isVerified": true,
                "createdDateTime": "2015-06-14T15:35:41.921Z",
                "reviewSourceName": "AFS",
                "verificationSource": "invitation",
                "verificationLevel": null,
                "hasDachExclusion": false
            }
        },
        "title": "EXCELLENT",
        "likes": 0,
        "source": "AFS",
        "dates": {
            "experiencedDate": null,
            "publishedDate": "2015-06-14T15:35:41.921Z",
            "updatedDate": null,
            "submittedDate": null
        },
        "report": null,
        "hasUnhandledReports": false,
        "consumer": {
            "id": "557d9f4d0000ff0001c5e491",
            "displayName": "JJM Marketing LLC",
            "imageUrl": "",
            "numberOfReviews": 1,
            "countryCode": "US",
            "hasImage": false,
            "isVerified": false
        },
        "reply": null,
        "consumersReviewCountOnSameDomain": 1,
        "consumersReviewCountOnSameLocation": null,
        "productReviews": [],
        "language": "en",
        "location": null
    },
    {
        "id": "557d97b00000ff0002edf7bb",
        "filtered": false,
        "pending": false,
        "text": "ordering was easy, service was prompt. Checka are printed nicely.",
        "rating": 5,
        "labels": {
            "merged": null,
            "verification": {
                "isVerified": true,
                "createdDateTime": "2015-06-14T15:03:12.400Z",
                "reviewSourceName": "AFS",
                "verificationSource": "invitation",
                "verificationLevel": null,
                "hasDachExclusion": false
            }
        },
        "title": "I really like the checks we ordered.",
        "likes": 0,
        "source": "AFS",
        "dates": {
            "experiencedDate": null,
            "publishedDate": "2015-06-14T15:03:12.400Z",
            "updatedDate": null,
            "submittedDate": null
        },
        "report": null,
        "hasUnhandledReports": false,
        "consumer": {
            "id": "557d97af0000ff0001c5e357",
            "displayName": "linda/jeff robertson",
            "imageUrl": "",
            "numberOfReviews": 1,
            "countryCode": "US",
            "hasImage": false,
            "isVerified": false
        },
        "reply": null,
        "consumersReviewCountOnSameDomain": 1,
        "consumersReviewCountOnSameLocation": null,
        "productReviews": [],
        "language": "en",
        "location": null
    },
    {
        "id": "557d837f0000ff0002edf39e",
        "filtered": false,
        "pending": false,
        "text": "I love the cost effective Carousel Checks offers. Also, the speed mailing service is a plus as well. I order all my checks through Carousel Checks.",
        "rating": 5,
        "labels": {
            "merged": null,
            "verification": {
                "isVerified": true,
                "createdDateTime": "2015-06-14T13:37:03.398Z",
                "reviewSourceName": "AFS",
                "verificationSource": "invitation",
                "verificationLevel": null,
                "hasDachExclusion": false
            }
        },
        "title": "Great service",
        "likes": 0,
        "source": "AFS",
        "dates": {
            "experiencedDate": null,
            "publishedDate": "2015-06-14T13:37:03.398Z",
            "updatedDate": null,
            "submittedDate": null
        },
        "report": null,
        "hasUnhandledReports": false,
        "consumer": {
            "id": "557d837f0000ff0001c5e011",
            "displayName": "M. THOMPSON",
            "imageUrl": "",
            "numberOfReviews": 5,
            "countryCode": "US",
            "hasImage": false,
            "isVerified": false
        },
        "reply": null,
        "consumersReviewCountOnSameDomain": 1,
        "consumersReviewCountOnSameLocation": null,
        "productReviews": [],
        "language": "en",
        "location": null
    },
    {
        "id": "557c9ac90000ff0002edd6cb",
        "filtered": false,
        "pending": false,
        "text": "Since my bank instituted new rules that did not allow me to bank with them anymore, I had to change over to a credit union, which meant for me new checks. I looked at the previous place I had used and wondered if I could get a better deal on-line elsewhere. So, I ordered from Carousel Checks because they had low prices for plain checks and deposit slips. The ordering was fairly straightforward and the checks/deposit slips arrived in record time. Head's up: The checks & deposit slips I ordered did not come in boxes like I had ordered from other check companies, so unless you wish to leave them in the mailing envelope they come in, you might want to have some boxes on hand to store your blank checks in.",
        "rating": 4,
        "labels": {
            "merged": null,
            "verification": {
                "isVerified": true,
                "createdDateTime": "2015-06-13T21:04:09.827Z",
                "reviewSourceName": "AFS",
                "verificationSource": "invitation",
                "verificationLevel": null,
                "hasDachExclusion": false
            }
        },
        "title": "No Fuss or Muss",
        "likes": 0,
        "source": "AFS",
        "dates": {
            "experiencedDate": null,
            "publishedDate": "2015-06-13T21:04:09.827Z",
            "updatedDate": null,
            "submittedDate": null
        },
        "report": null,
        "hasUnhandledReports": false,
        "consumer": {
            "id": "557c9ac90000ff0001c5c86d",
            "displayName": "Resnictem",
            "imageUrl": "",
            "numberOfReviews": 3,
            "countryCode": "US",
            "hasImage": false,
            "isVerified": false
        },
        "reply": null,
        "consumersReviewCountOnSameDomain": 1,
        "consumersReviewCountOnSameLocation": null,
        "productReviews": [],
        "language": "en",
        "location": null
    },
    {
        "id": "557c8d790000ff0002edd447",
        "filtered": false,
        "pending": false,
        "text": "Cheap expensive. Need to try and return.",
        "rating": 1,
        "labels": {
            "merged": null,
            "verification": {
                "isVerified": true,
                "createdDateTime": "2015-06-13T20:07:21.000Z",
                "reviewSourceName": "AFS",
                "verificationSource": "invitation",
                "verificationLevel": null,
                "hasDachExclusion": false
            }
        },
        "title": "Desk check cover",
        "likes": 0,
        "source": "AFS",
        "dates": {
            "experiencedDate": null,
            "publishedDate": "2015-06-13T20:07:21.000Z",
            "updatedDate": null,
            "submittedDate": null
        },
        "report": null,
        "hasUnhandledReports": false,
        "consumer": {
            "id": "557c8d790000ff0001c5c662",
            "displayName": "Carol Robertson",
            "imageUrl": "",
            "numberOfReviews": 1,
            "countryCode": "US",
            "hasImage": false,
            "isVerified": false
        },
        "reply": {
            "message": "Hello Carol \n\nThank you for your order!\n\nWe are sorry to hear that you are unsatisfied with the online pricing we have. \n\nPlease feel free to contact us at 1-708-613-2452 or info@carouselchecks.com, we are available Monday - Friday 8am to 7pm CST.",
            "publishedDate": "2015-06-15T16:25:41.561Z",
            "updatedDate": null
        },
        "consumersReviewCountOnSameDomain": 1,
        "consumersReviewCountOnSameLocation": null,
        "productReviews": [],
        "language": "en",
        "location": null
    },
    {
        "id": "557c89c10000ff0002edd392",
        "filtered": false,
        "pending": false,
        "text": "I'll have to admit, I was very skeptical on buying the number of checks that I ordered, wondering .. are these going to be like tissue paper, etc?? The price just seemed too low, as I was used to paying double that, thru the bank. Happy to say that they are every bit as good, as my original bank checks have been. I'll definitely be back, when the need arises.",
        "rating": 5,
        "labels": {
            "merged": null,
            "verification": {
                "isVerified": true,
                "createdDateTime": "2015-06-13T19:51:29.222Z",
                "reviewSourceName": "AFS",
                "verificationSource": "invitation",
                "verificationLevel": null,
                "hasDachExclusion": false
            }
        },
        "title": "Great Quality!",
        "likes": 0,
        "source": "AFS",
        "dates": {
            "experiencedDate": null,
            "publishedDate": "2015-06-13T19:51:29.222Z",
            "updatedDate": null,
            "submittedDate": null
        },
        "report": null,
        "hasUnhandledReports": false,
        "consumer": {
            "id": "557c89c00000ff0001c5c5de",
            "displayName": "RMP",
            "imageUrl": "",
            "numberOfReviews": 6,
            "countryCode": "US",
            "hasImage": false,
            "isVerified": false
        },
        "reply": null,
        "consumersReviewCountOnSameDomain": 1,
        "consumersReviewCountOnSameLocation": null,
        "productReviews": [],
        "language": "en",
        "location": null
    },
    {
        "id": "557c86bc0000ff0002edd2ec",
        "filtered": false,
        "pending": false,
        "text": "my wife got the checks and did not tell me.  all OK.",
        "rating": 5,
        "labels": {
            "merged": null,
            "verification": {
                "isVerified": true,
                "createdDateTime": "2015-06-13T19:38:36.497Z",
                "reviewSourceName": "AFS",
                "verificationSource": "invitation",
                "verificationLevel": null,
                "hasDachExclusion": false
            }
        },
        "title": "great value",
        "likes": 0,
        "source": "AFS",
        "dates": {
            "experiencedDate": null,
            "publishedDate": "2015-06-13T19:38:36.497Z",
            "updatedDate": null,
            "submittedDate": null
        },
        "report": null,
        "hasUnhandledReports": false,
        "consumer": {
            "id": "557c86bc0000ff0001c5c562",
            "displayName": "Bruce H",
            "imageUrl": "",
            "numberOfReviews": 4,
            "countryCode": "US",
            "hasImage": false,
            "isVerified": false
        },
        "reply": null,
        "consumersReviewCountOnSameDomain": 1,
        "consumersReviewCountOnSameLocation": null,
        "productReviews": [],
        "language": "en",
        "location": null
    }
]